Metadata-Version: 2.1
Name: jack-web
Version: 0.0.3
Summary: a webinterface to patch jack connections
Home-page: https://github.com/ljurk/jack-web-patchbay
Author: Lukas Jurk
Author-email: ljurk@pm.me
License: GPLv3
Keywords: jack jack2 patchbay
Platform: UNKNOWN
Classifier: Programming Language :: Python :: 2
Classifier: Programming Language :: Python :: 3
